{
  "grade": "중2",
  "week": 25,
  "title": "공감적 대화와 말 관용구 편",
  "total": 18,
  "study": {
    "vocab": [
      { "word": "각박하다", "hanja": "刻(새길 각) 薄(얇을 박)", "meaning": "인정이 없고 삭막하다.", "example": "요즘 세상인심이 너무 각박한 것 같다." },
      { "word": "겸허하다", "hanja": "謙(겸손할 겸) 虛(빌 허)", "meaning": "스스로 자신을 낮추고 비우는 태도가 있다.", "example": "그 사람의 겸허한 모습이 마음에 들었다." },
      { "word": "경각심", "hanja": "警(경계할 경) 覺(깨달을 각) 心(마음 심)", "meaning": "정신을 차리고 주의 깊게 살피어 경계하는 마음.", "example": "화재 기사는 불에 대한 경각심을 일깨워 주었다." },
      { "word": "동조하다", "hanja": "同(같을 동) 調(고를 조)", "meaning": "남의 주장에 자기의 의견을 일치시키거나 보조를 맞추다.", "example": "나는 고개를 끄덕여 그에게 동조하는 태도를 보였다." },
      { "word": "맹목적", "hanja": "盲(눈멀 맹) 目(눈 목) 的(과녁 적)", "meaning": "주관이나 원칙이 없이 덮어놓고 행동하는. 또는 그런 것.", "example": "그녀는 부모님께 맹목적으로 순종했다." },
      { "word": "무안하다", "hanja": "無(없을 무) 顔(얼굴 안)", "meaning": "수줍거나 창피하여 볼 낯이 없다.", "example": "그는 무안할 정도로 나를 빤히 쳐다보았다." },
      { "word": "보편적", "hanja": "普(널리 보) 遍(두루 편) 的(과녁 적)", "meaning": "「1」 두루 널리 미치는. 「2」 모든 것에 공통되거나 들어맞는. 또는 그런 것.", "example": "드라마의 주된 주제는 보편적 감정이다. / 보편적이고 예외 없는 규칙을 찾기는 어렵다." },
      { "word": "비판적", "hanja": "批(비평할 비) 判(판가름할 판) 的(과녁 적)", "meaning": "현상이나 사물의 옳고 그름을 판단하여 밝히거나 잘못된 점을 지적하는. 또는 그런 것.", "example": "그는 매사에 비판적인 태도를 보이는 것이 문제이다." },
      { "word": "순화", "hanja": "醇(진한 순) 化(될 화)", "meaning": "「1」 정성 어린 가르침으로 감화함. 「2」 잡스러운 것을 걸러서 순수하게 함.", "example": "청소년 선도에는 처벌보다 순화가 중요하다. / 청소년의 언어 순화를 위해 노력이 필요하다." }
    ],
    "concept": [
      { "word": "공감적 대화", "hanja": "共(함께 공) 感(느낄 감) 的(과녁 적) 對(대할 대) 話(말할 화)", "meaning": "상대방의 생각을 이해하고 감정을 공유하면서 상호 작용이 충실하게 이루어지는 대화.", "example": "소극적 들어 주기(관심을 보이며 이어 가게 함) / 적극적 들어 주기(요약·재구성해 스스로 문제를 해결하도록 도움)." }
    ],
    "idiom": [
      { "word": "말꼬리를 잡다", "hanja": "(관용구)", "meaning": "남의 말 가운데서 잘못 표현된 부분의 약점을 잡다.", "example": "그는 말꼬리를 잡아 시비를 걸었다." },
      { "word": "말을 맞추다", "hanja": "(관용구)", "meaning": "제삼자에게 같은 말을 하기 위하여 다른 사람과 말의 내용이 다르지 않게 하다.", "example": "용의자들은 이미 말을 맞추었는지 똑같이 말했다." },
      { "word": "말허리를 자르다", "hanja": "(관용구)", "meaning": "상대방이 말하는 도중에 말을 중지시키다.", "example": "그는 내 말을 듣지도 않고 말허리를 자르고 돌아섰다." },
      { "word": "아쉬운 소리", "hanja": "(관용구)", "meaning": "없거나 부족하여 남에게 빌거나 꾸려고 구차하게 사정하는 말.", "example": "남한테 아쉬운 소리는 안 하고 살아왔다." },
      { "word": "토를 달다", "hanja": "(관용구)", "meaning": "어떤 말 끝에 그 말에 대하여 덧붙여 말하다.", "example": "그는 어른들 말씀에 토를 달다가 핀잔을 들었다." }
    ]
  },
  "questions": [
    { "num": 1, "type": "short", "section": "01~04 밑줄 친 어휘의 뜻을 <보기>에서 찾아 번호를 쓰시오.", "boxki": ["① 정성 어린 가르침으로 감화함.", "② 잡스러운 것을 걸러서 순수하게 함.", "③ 주관이나 원칙이 없이 덮어놓고 행동하는. 또는 그런 것.", "④ 현상이나 사물의 옳고 그름을 판단하여 밝히거나 잘못된 점을 지적하는. 또는 그런 것."], "stem": "많은 사람들이 우리말 순화에 힘쓰고 있다.", "answer": "②", "answers": ["2", "②"] },
    { "num": 2, "type": "short", "stem": "서구 문명의 맹목적 추종은 그릇된 것이다.", "answer": "③", "answers": ["3", "③"] },
    { "num": 3, "type": "short", "stem": "그의 말이라면 무조건 따를 것이 아니라 때로는 비판적 태도를 보일 필요가 있다.", "answer": "④", "answers": ["4", "④"] },
    { "num": 4, "type": "short", "stem": "그는 담임 선생님이 깊은 관심과 가르침으로 순화를 한 덕택에 새사람이 되었다.", "answer": "①", "answers": ["1", "①"] },
    { "num": 5, "type": "short", "section": "05~08 빈칸에 들어갈 어휘를 <보기>에서 골라 문맥에 맞게 쓰시오.", "boxki": ["각박하다", "겸허하다", "동조하다", "무안하다"], "stem": "세상인심이 이렇게 ( ) 줄은 미처 몰랐다.", "answer": "각박한", "answers": ["각박한", "각박할"] },
    { "num": 6, "type": "short", "stem": "그의 논리는 극단적이어서 ( ) 수 없었다.", "answer": "동조할" },
    { "num": 7, "type": "short", "stem": "그들은 선거 결과를 ( ) 받아들이겠다고 밝혔다.", "answer": "겸허하게", "answers": ["겸허하게", "겸허히"] },
    { "num": 8, "type": "short", "stem": "나는 어제 저지른 실수가 ( ) 사람들 앞에 나설 수가 없었다.", "answer": "무안하여", "answers": ["무안하여", "무안해"] },
    { "num": 9, "type": "short", "section": "09~10 다음 문장에 어울리는 어휘를 고르시오.", "stem": "그 사건은 시민들에게 안전에 대한 ( 경각심 / 경외심 )을 불러일으켰다.", "answer": "경각심" },
    { "num": 10, "type": "short", "stem": "사회 구성원 간의 갈등은 어느 사회에나 존재하는 ( 한정적 / 보편적 )인 현상이다.", "answer": "보편적" },
    { "num": 11, "type": "short", "section": "11~15 다음 뜻에 해당하는 관용구를 <보기>에서 찾아 번호를 쓰시오.", "boxki": ["① 토를 달다", "② 말을 맞추다", "③ 아쉬운 소리", "④ 말꼬리를 잡다", "⑤ 말허리를 자르다"], "stem": "상대방이 말하는 도중에 말을 중지시키다.", "answer": "⑤", "answers": ["5", "⑤"] },
    { "num": 12, "type": "short", "stem": "어떤 말 끝에 그 말에 대하여 덧붙여 말하다.", "answer": "①", "answers": ["1", "①"] },
    { "num": 13, "type": "short", "stem": "남의 말 가운데서 잘못 표현된 부분의 약점을 잡다.", "answer": "④", "answers": ["4", "④"] },
    { "num": 14, "type": "short", "stem": "없거나 부족하여 남에게 빌거나 꾸려고 구차하게 사정하는 말.", "answer": "③", "answers": ["3", "③"] },
    { "num": 15, "type": "short", "stem": "다른 사람과 말의 내용이 다르지 않게 하다.", "answer": "②", "answers": ["2", "②"] },
    { "num": 16, "type": "short", "section": "16 빈칸에 들어갈 개념을 쓰시오.", "stem": "상대방의 생각을 이해하고 감정을 공유하면서 상호 작용이 충실하게 이루어지는 대화를 ( )라고 한다.", "answer": "공감적 대화", "answers": ["공감적 대화", "공감적대화"] },
    { "num": 17, "type": "short", "section": "17~18 <보기>를 구분하시오. ① 관심을 보이며 화자가 이야기를 이어 가게 하는 듣기. ② 적극적으로 말을 구성하여 전달하는 듣기. ③ 상대를 향해 앉고 눈을 맞추며 집중하는 듣기. ④ 스스로 문제를 해결할 수 있게 도와주는 듣기.", "stem": "소극적 들어 주기에 해당하는 번호를 모두 쓰시오.", "answer": "1, 3", "answers": ["1,3", "3,1", "13"] },
    { "num": 18, "type": "short", "stem": "적극적 들어 주기에 해당하는 번호를 모두 쓰시오.", "answer": "2, 4", "answers": ["2,4", "4,2", "24"] }
  ]
}
